arklibrary/__init__.py
arklibrary/config.ini
arklibrary/admin/__init__.py
arklibrary/admin/admin.py
arklibrary/admin/bundle.py
arklibrary/admin/run_driver.py
arklibrary/blueprints/__init__.py
arklibrary/blueprints/ammunitions.py
arklibrary/blueprints/armours.py
arklibrary/blueprints/artifacts.py
arklibrary/blueprints/beacons.py
arklibrary/blueprints/chibis.py
arklibrary/blueprints/colors.py
arklibrary/blueprints/commands.py
arklibrary/blueprints/consumables.py
arklibrary/blueprints/creatures.py
arklibrary/blueprints/dyes.py
arklibrary/blueprints/eggs.py
arklibrary/blueprints/farming.py
arklibrary/blueprints/recipes.py
arklibrary/blueprints/resources.py
arklibrary/blueprints/saddles.py
arklibrary/blueprints/seeds.py
arklibrary/blueprints/skins.py
arklibrary/blueprints/structures.py
arklibrary/blueprints/tools.py
arklibrary/blueprints/trophies.py
arklibrary/blueprints/weapons.py
arklibrary/data_structures/__init__.py
arklibrary/data_structures/encoder.py
arklibrary/data_structures/stream.py
arklibrary/data_structures/tri.py
arklibrary/events/__init__.py
arklibrary/events/events.py
arklibrary/lib/__init__.py
arklibrary/lib/configuration.py
arklibrary/lib/console.py
arklibrary/lib/logger.py
arklibrary/lib/pathify.py
arklibrary/tools/__init__.py
arklibrary/tools/ark_generic_scraper.py
arklibrary/tools/ark_image_scraper.py
arklibrary/tools/aws.py
arklibrary/tools/clipboard.py
arklibrary/tools/config.py
arklibrary/tools/namecheap.py
arklibrary/tools/read.py
arklibrary-1.0.2.dist-info/LICENSE
arklibrary-1.0.2.dist-info/METADATA
arklibrary-1.0.2.dist-info/WHEEL
arklibrary-1.0.2.dist-info/top_level.txt
arklibrary-1.0.2.dist-info/RECORD
